parsetron/__init__.py
parsetron/parsetron.py
parsetron/grammars/__init__.py
parsetron/grammars/colored_light.py
parsetron/grammars/colors.py
parsetron/grammars/numbers.py
parsetron/grammars/times.py
parsetron-0.1.1.dist-info/DESCRIPTION.rst
parsetron-0.1.1.dist-info/METADATA
parsetron-0.1.1.dist-info/metadata.json
parsetron-0.1.1.dist-info/pbr.json
parsetron-0.1.1.dist-info/RECORD
parsetron-0.1.1.dist-info/top_level.txt
parsetron-0.1.1.dist-info/WHEEL
