Metadata-Version: 2.0
Name: parsetron
Version: 0.1.1
Summary: A natural language semantic parser
Home-page: https://github.com/Kitt-AI/parsetron
Author: KITT.AI
Author-email: kittdotai@gmail.com
License: Apache
Keywords: parsetron
Platform: UNKNOWN
Classifier: Development Status :: 2 - Pre-Alpha
Classifier: Intended Audience :: Developers
Classifier: License :: OSI Approved :: Apache Software License
Classifier: Natural Language :: English
Classifier: Programming Language :: Python :: 2
Classifier: Programming Language :: Python :: 2.7
Classifier: Programming Language :: Python :: Implementation :: PyPy
